mimamori/__init__.py
mimamori/config.py
mimamori/console.py
mimamori/download.py
mimamori/environment.py
mimamori/globals.py
mimamori/main.py
mimamori/mihomo_api.py
mimamori/mihomo_config.py
mimamori/systemd.py
mimamori/utils.py
mimamori-0.3.3.dist-info/METADATA
mimamori-0.3.3.dist-info/WHEEL
mimamori-0.3.3.dist-info/entry_points.txt
mimamori-0.3.3.dist-info/licenses/LICENSE
mimamori-0.3.3.dist-info/RECORD
