Metadata-Version: 2.4
Name: mimamori
Version: 0.3.3
Summary: A lightweight CLI for Mihomo proxy management in restricted environments
Project-URL: Homepage, https://github.com/helium777/mimamori
Project-URL: Bug Tracker, https://github.com/helium777/mimamori/issues
Author-email: Helium7 <helium747@gmail.com>
License: MIT
License-File: LICENSE
Classifier: Development Status :: 3 - Alpha
Classifier: Environment :: Console
Classifier: Intended Audience :: Developers
Classifier: License :: OSI Approved :: MIT License
Classifier: Operating System :: POSIX :: Linux
Classifier: Programming Language :: Python :: 3
Classifier: Programming Language :: Python :: 3 :: Only
Classifier: Programming Language :: Python :: 3.11
Classifier: Programming Language :: Python :: 3.12
Classifier: Topic :: Internet :: Proxy Servers
Classifier: Topic :: System :: Networking
Classifier: Topic :: Utilities
Requires-Python: >=3.11
Requires-Dist: click>=8.1.8
Requires-Dist: pydantic-settings>=2.8.1
Requires-Dist: pyyaml>=6.0.2
Requires-Dist: requests>=2.32.3
Requires-Dist: rich>=14.0.0
Requires-Dist: tomlkit>=0.13.2
